LICENSE.txt
MANIFEST.in
README.md
pyproject.toml
setup.py
src/gamesbyexample/__crashdetector__.py
src/gamesbyexample/__generatehashes__.py
src/gamesbyexample/__init__.py
src/gamesbyexample/__init__.pyc
src/gamesbyexample/__main__.py
src/gamesbyexample/__programdata__.py
src/gamesbyexample/__pyflakescheck__.bat
src/gamesbyexample/__terminalopener__.py
src/gamesbyexample/_originalFiles.zip
src/gamesbyexample/affinecipher.py
src/gamesbyexample/alphabetizequiz.py
src/gamesbyexample/alphabetizewordquiz.py
src/gamesbyexample/analogclock.py
src/gamesbyexample/bagels.py
src/gamesbyexample/barca.py
src/gamesbyexample/beep0.wav
src/gamesbyexample/beep1.wav
src/gamesbyexample/beep2.wav
src/gamesbyexample/beep3.wav
src/gamesbyexample/birthdayparadox.py
src/gamesbyexample/bitmapmessage.py
src/gamesbyexample/blackjack.py
src/gamesbyexample/bouncingDots.py
src/gamesbyexample/bouncingLines.py
src/gamesbyexample/bouncingdots.py
src/gamesbyexample/bouncingdvd.py
src/gamesbyexample/bouncinglines.py
src/gamesbyexample/bricks.py
src/gamesbyexample/caesarcipher.py
src/gamesbyexample/caesarhacker.py
src/gamesbyexample/calendar_2019_11.txt
src/gamesbyexample/calendar_2019_6.txt
src/gamesbyexample/calendar_2020_3.txt
src/gamesbyexample/calendar_2020_4.txt
src/gamesbyexample/calendar_2021_2.txt
src/gamesbyexample/calendar_2029_12.txt
src/gamesbyexample/calendarmaker.py
src/gamesbyexample/carrotinabox.py
src/gamesbyexample/chancecheckers.py
src/gamesbyexample/chase.py
src/gamesbyexample/checkers.py
src/gamesbyexample/chohan.py
src/gamesbyexample/chomp.py
src/gamesbyexample/clickbait.py
src/gamesbyexample/coinflipsimulator.py
src/gamesbyexample/collatz.py
src/gamesbyexample/collatzstats.py
src/gamesbyexample/commonenglishwords.txt
src/gamesbyexample/conwaysgameoflife.py
src/gamesbyexample/conwaysgameoflife1.py
src/gamesbyexample/conwaysgameoflife2.py
src/gamesbyexample/copyToBookFolder.bat
src/gamesbyexample/countdown.py
src/gamesbyexample/countingquiz.py
src/gamesbyexample/deepcave.py
src/gamesbyexample.egg-info/PKG-INFO
src/gamesbyexample.egg-info/SOURCES.txt
src/gamesbyexample.egg-info/dependency_links.txt
src/gamesbyexample.egg-info/requires.txt
src/gamesbyexample.egg-info/top_level.txt
