Metadata-Version: 2.1
Name: gamesbyexample
Version: 2020.12.30
Summary: A collection of games (with source code) to use for example programming lessons.
Home-page: https://github.com/asweigart/pythonstdiogames
Author: Al Sweigart
Author-email: al@inventwithpython.com
License: MIT
Keywords: games
Platform: UNKNOWN
Classifier: License :: OSI Approved :: MIT License
Classifier: Programming Language :: Python
Classifier: Programming Language :: Python :: 3
Classifier: Programming Language :: Python :: 3.4
Classifier: Programming Language :: Python :: 3.5
Classifier: Programming Language :: Python :: 3.6
Classifier: Programming Language :: Python :: 3.7
Classifier: Programming Language :: Python :: 3.8
Classifier: Programming Language :: Python :: 3.9
